Metadata-Version: 1.1
Name: mkpydisable
Version: 0.1.0
Summary: Disable things in Python
Home-page: https://github.com/MichaelKim0407/mkpydisable
Author: Michael Kim
Author-email: jinzheng19930407@sina.com
License: MIT
Platform: UNKNOWN
Classifier: Development Status :: 3 - Alpha
Classifier: Intended Audience :: Developers
Classifier: License :: OSI Approved :: MIT License
Classifier: Programming Language :: Python :: 2.7
Classifier: Programming Language :: Python :: 3.3
Classifier: Programming Language :: Python :: 3.4
Classifier: Programming Language :: Python :: 3.5
Classifier: Topic :: Software Development :: Libraries
